README.md
setup.py
mountwizzard4_arm.egg-info/PKG-INFO
mountwizzard4_arm.egg-info/SOURCES.txt
mountwizzard4_arm.egg-info/dependency_links.txt
mountwizzard4_arm.egg-info/requires.txt
mountwizzard4_arm.egg-info/top_level.txt
mountwizzard4_arm.egg-info/zip-safe
mw4/__init__.py
mw4/definitions.py
mw4/loader.py
mw4/mainApp.py
mw4/astrometry/__init__.py
mw4/astrometry/astrometry.py
mw4/astrometry/astrometryASTAP.py
mw4/astrometry/astrometryNET.py
mw4/base/__init__.py
mw4/base/indiClass.py
mw4/base/measuredata.py
mw4/base/tpool.py
mw4/base/transform.py
mw4/cover/__init__.py
mw4/cover/flipflat.py
mw4/dome/__init__.py
mw4/dome/dome.py
mw4/environment/__init__.py
mw4/environment/environ.py
mw4/environment/skymeter.py
mw4/environment/weather.py
mw4/gui/__init__.py
mw4/gui/hemisphereW.py
mw4/gui/imageW.py
mw4/gui/mainW.py
mw4/gui/measureW.py
mw4/gui/messageW.py
mw4/gui/mount3D.py
mw4/gui/satelliteW.py
mw4/gui/splash.py
mw4/gui/styles.py
mw4/gui/widget.py
mw4/gui/mainWmixin/__init__.py
mw4/gui/mainWmixin/tabBuildPoints.py
mw4/gui/mainWmixin/tabEnviron.py
mw4/gui/mainWmixin/tabManageModel.py
mw4/gui/mainWmixin/tabModel.py
mw4/gui/mainWmixin/tabMount.py
mw4/gui/mainWmixin/tabPower.py
mw4/gui/mainWmixin/tabRelay.py
mw4/gui/mainWmixin/tabSatellite.py
mw4/gui/mainWmixin/tabSettDevice.py
mw4/gui/mainWmixin/tabSettHorizon.py
mw4/gui/mainWmixin/tabSettImaging.py
mw4/gui/mainWmixin/tabSettIndi.py
mw4/gui/mainWmixin/tabSettMisc.py
mw4/gui/mainWmixin/tabSettMount.py
mw4/gui/mainWmixin/tabSettParkPos.py
mw4/gui/mainWmixin/tabSettRelay.py
mw4/gui/mainWmixin/tabTools.py
mw4/gui/widgets/__init__.py
mw4/gui/widgets/hemisphere_ui.py
mw4/gui/widgets/image_ui.py
mw4/gui/widgets/main_ui.py
mw4/gui/widgets/measure_ui.py
mw4/gui/widgets/message_ui.py
mw4/gui/widgets/satellite_ui.py
mw4/imaging/__init__.py
mw4/imaging/camera.py
mw4/modeldata/__init__.py
mw4/modeldata/alignstars.py
mw4/modeldata/buildpoints.py
mw4/modeldata/hipparcos.py
mw4/powerswitch/__init__.py
mw4/powerswitch/kmRelay.py
mw4/powerswitch/pegasusUPB.py
mw4/remote/__init__.py
mw4/remote/remote.py
mw4/resource/__init__.py
mw4/resource/resources.py
mw4/telescope/__init__.py
mw4/telescope/telescope.py